unitree_cli/__init__.py
unitree_cli/cli/__init__.py
unitree_cli/cli/main.py
unitree_cli/tools/__init__.py
unitree_cli/tools/joystick.py
unitree_cli-0.0.3.dist-info/METADATA
unitree_cli-0.0.3.dist-info/WHEEL
unitree_cli-0.0.3.dist-info/entry_points.txt
unitree_cli-0.0.3.dist-info/top_level.txt
unitree_cli-0.0.3.dist-info/RECORD
