Metadata-Version: 2.4
Name: unitree_cli
Version: 0.0.3
Summary: Unitree Cli Tools
Author: Agnel Wang
Author-email: 2273421791wk@gmail.com
License: Apache License 2.0
Classifier: Programming Language :: Python :: 3
Classifier: License :: OSI Approved :: Apache Software License
Classifier: Operating System :: OS Independent
Requires-Dist: rich-click
Requires-Dist: paramiko
Requires-Dist: unitree_dds_wrapper>=2.0.7
Dynamic: author
Dynamic: author-email
Dynamic: classifier
Dynamic: license
Dynamic: requires-dist
Dynamic: summary
